youtubewatched/__init__.py
youtubewatched/__main__.py
youtubewatched/config.py
youtubewatched/convert_takeout.py
youtubewatched/dash_layout.py
youtubewatched/main.py
youtubewatched/topics.py
youtubewatched/write_to_sql.py
youtubewatched/youtube.py
youtubewatched/dashing/__init__.py
youtubewatched/dashing/overrides.py
youtubewatched/get_data/__init__.py
youtubewatched/get_data/history_chart.py
youtubewatched/get_data/misc.py
youtubewatched/get_data/tracking.py
youtubewatched/get_data/videos_scatter_graph.py
youtubewatched/manage_records/__init__.py
youtubewatched/manage_records/views.py
youtubewatched/new_project/__init__.py
youtubewatched/new_project/views.py
youtubewatched/static/dash_graph.css
youtubewatched/static/favicon.png
youtubewatched/static/main.css
youtubewatched/static/js/create_project.js
youtubewatched/static/js/helpers.js
youtubewatched/static/js/manage_takeout.js
youtubewatched/templates/base.html
youtubewatched/templates/flash_messages.html
youtubewatched/templates/index.html
youtubewatched/templates/new_project.html
youtubewatched/templates/help/setup_project_help.html
youtubewatched/templates/help/takeout_help.html
youtubewatched/utils/__init__.py
youtubewatched/utils/app.py
youtubewatched/utils/gen.py
youtubewatched/utils/sql.py
youtubewatched-0.1.4.dist-info/LICENSE
youtubewatched-0.1.4.dist-info/METADATA
youtubewatched-0.1.4.dist-info/WHEEL
youtubewatched-0.1.4.dist-info/entry_points.txt
youtubewatched-0.1.4.dist-info/top_level.txt
youtubewatched-0.1.4.dist-info/RECORD
