Metadata-Version: 2.1
Name: youtubewatched
Version: 0.1.4
Summary: Visualization of Youtube watch history from Google Takeout
Home-page: https://github.com/VldmrB/youtube-watched
Author: Vladimir Belitskiy
Author-email: belitskiy@gmail.com
License: MIT
Keywords: visualization youtube takeout
Platform: UNKNOWN
Classifier: License :: OSI Approved :: MIT License
Classifier: Programming Language :: Python
Classifier: Programming Language :: Python :: 3
Classifier: Programming Language :: Python :: 3.6
Classifier: Programming Language :: Python :: 3.7
Classifier: Programming Language :: Python :: Implementation :: CPython
Classifier: Operating System :: OS Independent
Classifier: Framework :: Flask
Requires-Python: >=3.6.0
Requires-Dist: beautifulsoup4 (==4.7.1)
Requires-Dist: dash (==0.40.0)
Requires-Dist: Flask (==1.0.2)
Requires-Dist: google-api-python-client (==1.7.8)
Requires-Dist: lxml (==4.3.3)
Requires-Dist: numpy (==1.16.2)
Requires-Dist: pandas (==0.24.2)
Requires-Dist: plotly (==3.7.1)
